pypicsum/__init__.py
pypicsum/pypicsum.py
PyPicsum-1.0.0b1.dist-info/LICENCE
PyPicsum-1.0.0b1.dist-info/METADATA
PyPicsum-1.0.0b1.dist-info/WHEEL
PyPicsum-1.0.0b1.dist-info/top_level.txt
PyPicsum-1.0.0b1.dist-info/RECORD
